rustools-0.1.0.dist-info/METADATA
rustools-0.1.0.dist-info/WHEEL
rustools/__init__.py
rustools/rustools.cp313-win_amd64.pyd
rustools/rustools.pyi
rustools-0.1.0.dist-info/RECORD
