Metadata-Version: 2.4
Name: rustools
Version: 0.1.0
Classifier: Programming Language :: Rust
Classifier: Programming Language :: Python :: Implementation :: CPython
Classifier: Programming Language :: Python :: Implementation :: PyPy
Summary: 基于rust pyo3开发python扩展
License: MIT
Requires-Python: >=3.9
